LICENSE
README.md
powerdnsapi/__init__.py
powerdnsapi/powerdnsapi.py
powerdnsapi-0.0.1.dist-info/METADATA
powerdnsapi-0.0.1.dist-info/LICENSE
powerdnsapi-0.0.1.dist-info/WHEEL
powerdnsapi-0.0.1.dist-info/RECORD
