Metadata-Version: 2.1
Name: powerdnsapi
Version: 0.0.1
Summary: Python PowerDNS API tool for interacting with Authoritative PowerDNS Servers
Home-page: https://github.com/nlgotz/powerdnsapi
License: Apache 2.0
Author: Nate Gotz
Author-email: 775979+nlgotz@users.noreply.github.com
Requires-Python: >=3.8,<4.0
Classifier: License :: Other/Proprietary License
Classifier: Programming Language :: Python :: 3
Classifier: Programming Language :: Python :: 3.8
Classifier: Programming Language :: Python :: 3.9
Classifier: Programming Language :: Python :: 3.10
Classifier: Programming Language :: Python :: 3.11
Requires-Dist: jsonref
Requires-Dist: jsonschema
Project-URL: Repository, https://github.com/nlgotz/powerdnsapi
